infi_multi_db/__init__.py
infi_multi_db/multiDB.py
infi_multi_db/handlers/__init__.py
infi_multi_db/handlers/postgresql.py
infi_multi_db-0.0.4.dist-info/METADATA
infi_multi_db-0.0.4.dist-info/WHEEL
infi_multi_db-0.0.4.dist-info/top_level.txt
infi_multi_db-0.0.4.dist-info/RECORD
