Metadata-Version: 2.1
Name: infi-multi-db
Version: 0.0.4
Summary: Package for using multi DBs for Infinity team
Author: Infinity Team
License: MIT
Requires-Dist: psycopg2-binary
